v2conf/__init__.py
v2conf/__main__.py
v2conf/configs.py
v2conf/exclude.py
v2conf/health.py
v2conf-0.2.0.dist-info/LICENSE
v2conf-0.2.0.dist-info/METADATA
v2conf-0.2.0.dist-info/WHEEL
v2conf-0.2.0.dist-info/entry_points.txt
v2conf-0.2.0.dist-info/RECORD
