Metadata-Version: 2.1
Name: v2conf
Version: 0.2.0
Summary: V2Conf helps you build V2Ray Config file automatically and evaluate and change config rules based on outbounds performances.
Home-page: https://github.com/mahyar24/V2Conf/
License: GPL-3.0-or-later
Keywords: V2Ray,V2Fly,X2Ray
Author: Mahyar Mahdavi
Author-email: Mahyar@Mahyar24.com
Requires-Python: >=3.9,<4.0
Classifier: License :: OSI Approved :: GNU General Public License v3 or later (GPLv3+)
Classifier: Programming Language :: Python :: 3
Classifier: Programming Language :: Python :: 3.9
Classifier: Programming Language :: Python :: 3.10
Classifier: Programming Language :: Python :: 3.11
Classifier: Programming Language :: Python :: 3.12
Requires-Dist: aiohttp (==3.12.14)
Requires-Dist: jdatetime (>=4.1.0,<5.0.0)
Requires-Dist: json5kit (>=0.3.2,<0.4.0)
Requires-Dist: requests (>=2.28.1,<3.0.0)
Project-URL: Repository, https://github.com/Mahyar24/V2Conf/
